{
  "page-title": "CampMinder Dashboard",
  "channel-status-card-title": "Channel status",
  "channel-status-card-active-subtitle": "Active channels",
  "channel-status-delay-description": "Experiencing delays",
  "channel-status-awaiting-setup-description": "Awaiting setup",
  "channel-status-rate-disabled-description": "Channel campsite rate disabled",
  "channel-status-connection-interrupted-description": "Channel connection interrupted",
  "channel-status-less-channels-button": "Less channels",
  "channel-status-more-channels-button": "More channels",
  "reservations-card": {
    "title": "Today's reservations",
    "action": "Edit card",
    "arrivals": "Arrivals",
    "departures": "Departures",
    "new-bookings": "New bookings",
    "stays": "Stays",
    "cancellations": "Cancellations"
  },
  "notifications-card": {
    "title": "Notifications",
    "action": "Edit card",
    "small": "Small",
    "medium": "Medium",
    "large": "Large",
    "default": "Default",
    "success": "Success",
    "warning": "Warning",
    "alert": "Alert",
    "disabled": "Disabled",
    "sm-loading-image": "sm-loading-image"
  },
  "camp-status-card": {
    "title": "Camp site status",
    "action": "Edit card",
    "sm-loader": "sm-loader",
    "sm-loading-card": "sm-loading-card"
  },
  "smart-guide-card": {
    "title": "Smart Guide",
    "action": "Edit card",
    "sm-loading-form": "sm-loading-form",
    "sm-loading-home-screen": "sm-loading-home-screen"
  },
  "upsell-card": {
    "hotel-app-store": {
      "title": "SiteMinder hotel app store",
      "content": "Apps and integrations to optimise your business.",
      "learn-more-action": "Learn more"
    }
  },
  "inline-card": {
    "general-info-inline-card-header-text": "General Info",
    "reservations": {
      "title": "Today's reservations",
      "message": "Schedule",
      "body": "Check-in for the camp will begin in the morning for the first day. The camp will officially start with a group orientation lecture. Check-out will be at the completion of the Award Ceremony",
      "more-info-button-text": "More info"
    },
    "notifications": {
      "title": "Training",
      "message": "Notifications",
      "body": "Three training sessions per day (morning, afternoon and evening). Play heaps of officiated games, maybe your team will be the champions of your age group. It is not compulsory for a child to attend the evening session but it is highly recommended. Players train and play in their own age groups.",
      "more-info-button-text": "More info",
      "content": "Apps and integrations to optimise your business."
    },
    "warning": {
      "warning-info": "Warnings",
      "title": "Activity risk warning",
      "message": "Camp site status",
      "body": "Campers may undertake supervised activities on camp that could possibly cause injury.",
      "more-info-button-text": "More info"
    }
  }
}
